<!DOCTYPE rkplugin>
<document>
	<code file="uniform_probabilities.php" />
	<snippets>
		<snippet id="dist_options">
			<spinbox default_precision="2" type="real" initial="0" id="min" label="Lower limit of the distribution"/>
			<spinbox default_precision="2" type="real" initial="1" id="max" label="Upper limit of the distribution"/>
		</snippet>
		<include file="dist_snippets.xml"/>
	</snippets>
	<dialog label="Uniform probabilities" >
		<insert snippet="probabilities_layout"/>
	</dialog>
</document>
